tokentap/__init__.py
tokentap/cli.py
tokentap/config.py
tokentap/dashboard.py
tokentap/parser.py
tokentap/proxy.py
tokentap-0.1.0.dist-info/licenses/LICENSE
tokentap-0.1.0.dist-info/METADATA
tokentap-0.1.0.dist-info/WHEEL
tokentap-0.1.0.dist-info/entry_points.txt
tokentap-0.1.0.dist-info/top_level.txt
tokentap-0.1.0.dist-info/RECORD
