Metadata-Version: 2.4
Name: tokentap
Version: 0.1.0
Summary: Token tracker for LLM CLI tools with live terminal dashboard
Author: Juan Munoz
License: MIT
Project-URL: Homepage, https://tokentap.ai
Project-URL: Repository, https://github.com/jmuncor/tokentap
Project-URL: Issues, https://github.com/jmuncor/tokentap/issues
Keywords: llm,tokens,claude,anthropic,openai,gemini,cli,token-tracking
Classifier: Development Status :: 4 - Beta
Classifier: Environment :: Console
Classifier: Intended Audience :: Developers
Classifier: License :: OSI Approved :: MIT License
Classifier: Programming Language :: Python :: 3
Classifier: Programming Language :: Python :: 3.10
Classifier: Programming Language :: Python :: 3.11
Classifier: Programming Language :: Python :: 3.12
Classifier: Programming Language :: Python :: 3.13
Classifier: Topic :: Software Development
Classifier: Topic :: Utilities
Requires-Python: >=3.10
License-File: LICENSE
Requires-Dist: aiohttp>=3.9.0
Requires-Dist: rich>=13.0.0
Requires-Dist: tiktoken>=0.5.0
Requires-Dist: click>=8.0.0
Provides-Extra: dev
Requires-Dist: pytest; extra == "dev"
Requires-Dist: build; extra == "dev"
Requires-Dist: twine; extra == "dev"
Dynamic: license-file
